uncertain/__init__.py
uncertain/uncertain.py
uncertain-0.0.13.dist-info/LICENSE
uncertain-0.0.13.dist-info/METADATA
uncertain-0.0.13.dist-info/WHEEL
uncertain-0.0.13.dist-info/top_level.txt
uncertain-0.0.13.dist-info/RECORD
