Metadata-Version: 2.1
Name: uncertain
Version: 0.0.13
Summary: A Python 3 package for mathematical calculations with         uncertain numbers
Home-page: https://gitlab.com/mnn/uncertain
Author: M. Nuño
Author-email: mnunos@outlook.com
Project-URL: Documentation, https://mnn.gitlab.io/uncertain/
Project-URL: Source, https://gitlab.com/mnn/uncertain
Project-URL: Bug Reports, https://gitlab.com/mnn/uncertain/-/issues
Classifier: Development Status :: 4 - Beta
Classifier: Intended Audience :: Science/Research
Classifier: License :: OSI Approved :: GNU General Public License v3 (GPLv3)
Classifier: Programming Language :: Python
Requires-Python: >=3.6
License-File: LICENSE
Requires-Dist: numpy
Requires-Dist: scipy
Requires-Dist: matplotlib
